{"ideaGroups":[{"isUnique":false,"countryTag":"aristocracy","type":"aristocracy_ideas","category":"MIL","ideas":[{"name":"bonus","order":0,"bonuses":[{"type":"leader_siege","value":"1"},{"type":"nobles_loyalty_modifier","value":"0.2"}]},{"name":"noble_knights","order":1,"bonuses":[{"type":"cavalry_power","value":"0.15"},{"type":"cavalry_cost","value":"-0.05"}]},{"name":"military_traditions","order":2,"bonuses":[{"type":"mil_tech_cost_modifier","value":"-0.1"},{"type":"army_tradition_from_battle","value":"1"}]},{"name":"local_nobility","order":3,"bonuses":[{"type":"global_autonomy","value":"-0.05"},{"type":"yearly_absolutism","value":"6"}]},{"name":"serfdom","order":4,"bonuses":[{"type":"global_manpower_modifier","value":"0.33"}]},{"name":"noble_officers","order":5,"bonuses":[{"type":"army_tradition_decay","value":"-0.01"},{"type":"navy_tradition_decay","value":"-0.01"}]},{"name":"noble_resilience","order":6,"bonuses":[{"type":"general_cost","value":"-0.20"}]},{"name":"international_nobility","order":7,"bonuses":[{"type":"fire_damage_received","value":"-0.1"}]}],"important":false},{"isUnique":false,"countryTag":"plutocracy","type":"plutocracy_ideas","category":"MIL","ideas":[{"name":"bonus","order":0,"bonuses":[{"type":"fire_damage","value":"0.1"},{"type":"burghers_loyalty_modifier","value":"0.1"},{"type":"vaisyas_loyalty_modifier","value":"0.1"}]},{"name":"bill_of_rights","order":1,"bonuses":[{"type":"infantry_cost","value":"-0.125"}]},{"name":"abolished_serfdom","order":2,"bonuses":[{"type":"land_morale","value":"0.10"}]},{"name":"tradition_of_payment","order":3,"bonuses":[{"type":"mercenary_cost","value":"-0.2"},{"type":"mercenary_discipline","value":"0.03"}]},{"name":"free_merchants","order":4,"bonuses":[{"type":"merchants","value":"1"}]},{"name":"free_subjects","order":5,"bonuses":[{"type":"global_trade_goods_size_modifier","value":"0.1"}]},{"name":"free_cities","order":6,"bonuses":[{"type":"caravan_power","value":"0.5"}]},{"name":"emancipation","order":7,"bonuses":[{"type":"manpower_recovery_speed","value":"0.2"}]}],"important":false},{"isUnique":false,"countryTag":"innovativeness","type":"innovativeness_ideas","category":"ADM","ideas":[{"name":"bonus","order":0,"bonuses":[{"type":"possible_mil_policy","value":"1"}]},{"name":"scientific_revolution","order":1,"bonuses":[{"type":"technology_cost","value":"-0.1"},{"type":"embracement_cost","value":"-0.1"}]},{"name":"empiricism","order":2,"bonuses":[{"type":"innovativeness_gain","value":"1"}]},{"name":"patron_of_art","order":3,"bonuses":[{"type":"prestige_decay","value":"-0.01"}]},{"name":"dynamic_court","order":4,"bonuses":[{"type":"idea_cost","value":"-0.1"}]},{"name":"print_culture","order":5,"bonuses":[{"type":"drill_decay_modifier","value":"-0.1"}]},{"name":"optimism","order":6,"bonuses":[{"type":"war_exhaustion","value":"-0.05"}]},{"name":"formalized_officer_corps","order":7,"bonuses":[{"type":"free_leader_pool","value":"2"}]}],"important":false},{"isUnique":false,"countryTag":"religious","type":"religious_ideas","category":"ADM","ideas":[{"name":"bonus","order":0,"bonuses":[{"type":"culture_conversion_cost","value":"-0.25"},{"type":"brahmins_hindu_loyalty_modifier","value":"0.1"},{"type":"church_loyalty_modifier","value":"0.1"},{"type":"monthly_piety","value":"-0.001"}]},{"name":"deus_vult","order":1,"bonuses":[{"type":"cb_on_religious_enemies","value":"yes"},{"type":"warscore_cost_vs_other_religion","value":"-0.10"}]},{"name":"missionary_schools","order":2,"bonuses":[{"type":"missionaries","value":"1"}]},{"name":"church_attendance_duty","order":3,"bonuses":[{"type":"global_tax_modifier","value":"0.2"}]},{"name":"divine_supremacy","order":4,"bonuses":[{"type":"global_missionary_strength","value":"0.03"}]},{"name":"devoutness","order":5,"bonuses":[{"type":"tolerance_own","value":"2"},{"type":"papal_influence","value":"2"},{"type":"devotion","value":"0.5"},{"type":"monthly_fervor_increase","value":"0.25"},{"type":"church_power_modifier","value":"0.1"}]},{"name":"religious_tradition","order":6,"bonuses":[{"type":"prestige","value":"1"}]},{"name":"inquisition","order":7,"bonuses":[{"type":"manpower_in_true_faith_provinces","value":"0.15"}]}],"important":false},{"isUnique":false,"countryTag":"spy","type":"spy_ideas","category":"DIP","ideas":[{"name":"bonus","order":0,"bonuses":[{"type":"merchants","value":"1"}]},{"name":"efficient_spies","order":1,"bonuses":[{"type":"spy_offence","value":"0.75"},{"type":"advisor_cost","value":"-0.15"}]},{"name":"state_propaganda","order":2,"bonuses":[{"type":"ae_impact","value":"-0.2"},{"type":"curia_powers_cost","value":"-0.25"},{"type":"church_power_modifier","value":"0.2"},{"type":"yearly_harmony","value":"1"},{"type":"devotion","value":"0.5"}]},{"name":"vetting","order":3,"bonuses":[{"type":"trade_steering","value":"0.33"},{"type":"global_foreign_trade_power","value":"0.30"}]},{"name":"agent_training","order":4,"bonuses":[{"type":"power_projection_from_insults","value":"1"},{"type":"prestige","value":"0.75"}]},{"name":"claim_fabrication","order":5,"bonuses":[{"type":"embargo_efficiency","value":"0.33"},{"type":"yearly_corruption","value":"-0.5"}]},{"name":"privateers","order":6,"bonuses":[{"type":"artillery_bonus_vs_fort","value":"1"},{"type":"siege_ability","value":"0.10"}]},{"name":"audit_checks","order":7,"bonuses":[{"type":"movement_speed","value":"0.1"}]}],"important":false},{"isUnique":false,"countryTag":"diplomatic","type":"diplomatic_ideas","category":"DIP","ideas":[{"name":"bonus","order":0,"bonuses":[{"type":"reduced_stab_impacts","value":"yes"}]},{"name":"foreign_embassies","order":1,"bonuses":[{"type":"diplomats","value":"1"}]},{"name":"cabinet","order":2,"bonuses":[{"type":"diplomatic_upkeep","value":"1"}]},{"name":"grand_banquets","order":3,"bonuses":[{"type":"diplomats","value":"1"}]},{"name":"benign_diplomats","order":4,"bonuses":[{"type":"improve_relation_modifier","value":"0.25"}]},{"name":"experienced_diplomats","order":5,"bonuses":[{"type":"diplomatic_reputation","value":"2"}]},{"name":"flexible_negotiation","order":6,"bonuses":[{"type":"province_warscore_cost","value":"-0.2"}]},{"name":"diplomatic_corps","order":7,"bonuses":[{"type":"dip_tech_cost_modifier","value":"-0.1"}]}],"trigger":{"primatives":true,"tag":[]},"important":false},{"isUnique":false,"countryTag":"offensive","type":"offensive_ideas","category":"MIL","ideas":[{"name":"bonus","order":0,"bonuses":[{"type":"recover_army_morale_speed","value":"0.1"}]},{"name":"bayonet_leaders","order":1,"bonuses":[{"type":"leader_land_shock","value":"1"}]},{"name":"national_conscripts","order":2,"bonuses":[{"type":"movement_speed","value":"0.1"}]},{"name":"superior_firepower","order":3,"bonuses":[{"type":"leader_land_fire","value":"1"}]},{"name":"glorious_arms","order":4,"bonuses":[{"type":"prestige_from_land","value":"1.0"}]},{"name":"engineer_corps","order":5,"bonuses":[{"type":"siege_ability","value":"0.20"},{"type":"artillery_bonus_vs_fort","value":"1"}]},{"name":"grand_army","order":6,"bonuses":[{"type":"land_forcelimit_modifier","value":"0.2"}]},{"name":"napoleonic_warfare","order":7,"bonuses":[{"type":"discipline","value":"0.05"}]}],"important":false},{"isUnique":false,"countryTag":"defensive","type":"defensive_ideas","category":"MIL","ideas":[{"name":"bonus","order":0,"bonuses":[{"type":"shock_damage_received","value":"-0.1"}]},{"name":"battlefield_commisions","order":1,"bonuses":[{"type":"army_tradition_from_battle","value":"1.0"}]},{"name":"military_drill","order":2,"bonuses":[{"type":"land_morale","value":"0.10"}]},{"name":"improved_manuever","order":3,"bonuses":[{"type":"leader_land_manuever","value":"1"}]},{"name":"regimental_system","order":4,"bonuses":[{"type":"garrison_size","value":"0.25"}]},{"name":"defensive_mentality","order":5,"bonuses":[{"type":"defensiveness","value":"0.2"},{"type":"fort_maintenance_modifier","value":"-0.2"}]},{"name":"supply_trains","order":6,"bonuses":[{"type":"reinforce_speed","value":"0.33"}]},{"name":"improved_foraging","order":7,"bonuses":[{"type":"land_attrition","value":"-0.25"}]}],"important":false},{"isUnique":false,"countryTag":"trade","type":"trade_ideas","category":"DIP","ideas":[{"name":"bonus","order":0,"bonuses":[{"type":"merchants","value":"1"}]},{"name":"shrewd_commerce_practise","order":1,"bonuses":[{"type":"global_trade_power","value":"0.2"}]},{"name":"free_trade","order":2,"bonuses":[{"type":"merchants","value":"1"}]},{"name":"merchant_adventures","order":3,"bonuses":[{"type":"trade_range_modifier","value":"0.25"}]},{"name":"national_trade_policy","order":4,"bonuses":[{"type":"trade_efficiency","value":"0.1"}]},{"name":"overseas_merchants","order":5,"bonuses":[{"type":"merchants","value":"1"}]},{"name":"trade_manipulation","order":6,"bonuses":[{"type":"trade_steering","value":"0.25"}]},{"name":"fast_negotiations","order":7,"bonuses":[{"type":"caravan_power","value":"0.5"}]}],"important":false},{"isUnique":false,"countryTag":"economic","type":"economic_ideas","category":"ADM","ideas":[{"name":"bonus","order":0,"bonuses":[{"type":"global_trade_goods_size_modifier","value":"0.1"}]},{"name":"bureaucracy","order":1,"bonuses":[{"type":"global_tax_modifier","value":"0.15"}]},{"name":"organised_construction","order":2,"bonuses":[{"type":"build_cost","value":"-0.1"}]},{"name":"national_bank","order":3,"bonuses":[{"type":"inflation_reduction","value":"0.2"}]},{"name":"debt_and_loans","order":4,"bonuses":[{"type":"build_time","value":"-0.25"}]},{"name":"centralization","order":5,"bonuses":[{"type":"global_autonomy","value":"-0.05"}]},{"name":"nationalistic_enthusiasm","order":6,"bonuses":[{"type":"land_maintenance_modifier","value":"-0.1"}]},{"name":"smithian_economics","order":7,"bonuses":[{"type":"production_efficiency","value":"0.1"}]}],"important":false},{"isUnique":false,"countryTag":"exploration","type":"exploration_ideas","category":"DIP","ideas":[{"name":"bonus","order":0,"bonuses":[{"type":"cb_on_primitives","value":"yes"}]},{"name":"quest_for_the_new_world","order":1,"bonuses":[{"type":"may_explore","value":"yes"}]},{"name":"colonial_ventures","order":2,"bonuses":[{"type":"colonists","value":"1"}]},{"name":"overseas_exploration","order":3,"bonuses":[{"type":"range","value":"0.5"}]},{"name":"land_of_opportunity","order":4,"bonuses":[{"type":"global_colonial_growth","value":"10"}]},{"name":"vice_roys","order":5,"bonuses":[{"type":"global_tariffs","value":"0.10"},{"type":"envoy_travel_time","value":"-0.20"}]},{"name":"free_colonies","order":6,"bonuses":[{"type":"expel_minorities_cost","value":"-1.0"}]},{"name":"global_empire","order":7,"bonuses":[{"type":"naval_forcelimit_modifier","value":"0.25"}]}],"trigger":{"primatives":true,"tag":[]},"important":false},{"isUnique":false,"countryTag":"maritime","type":"maritime_ideas","category":"DIP","ideas":[{"name":"bonus","order":0,"bonuses":[{"type":"sea_repair","value":"yes"}]},{"name":"merchant_traditions","order":1,"bonuses":[{"type":"naval_tradition_from_trade","value":"1.0"}]},{"name":"merchant_marine","order":2,"bonuses":[{"type":"global_sailors_modifier","value":"0.25"}]},{"name":"sheltered_ports","order":3,"bonuses":[{"type":"global_ship_repair","value":"0.1"},{"type":"sailor_maintenance_modifer","value":"-0.1"}]},{"name":"grand_navy","order":4,"bonuses":[{"type":"naval_forcelimit_modifier","value":"0.5"}]},{"name":"ships_penny","order":5,"bonuses":[{"type":"global_ship_cost","value":"-0.1"}]},{"name":"sea_hawks","order":6,"bonuses":[{"type":"free_leader_pool","value":"1"},{"type":"admiral_cost","value":"-0.25"}]},{"name":"naval_fighting_instruction","order":7,"bonuses":[{"type":"blockade_efficiency","value":"0.5"},{"type":"trade_efficiency","value":"0.1"}]}],"trigger":{"primatives":true,"tag":[]},"important":false},{"isUnique":false,"countryTag":"quality","type":"quality_ideas","category":"MIL","ideas":[{"name":"bonus","order":0,"bonuses":[{"type":"discipline","value":"0.05"}]},{"name":"private_to_marshal","order":1,"bonuses":[{"type":"infantry_power","value":"0.1"}]},{"name":"quality_education","order":2,"bonuses":[{"type":"army_tradition","value":"0.5"}]},{"name":"finest_of_horses","order":3,"bonuses":[{"type":"cavalry_power","value":"0.1"}]},{"name":"escort_ships","order":4,"bonuses":[{"type":"ship_durability","value":"0.05"}]},{"name":"naval_drill","order":5,"bonuses":[{"type":"drill_decay_modifier","value":"-0.1"}]},{"name":"copper_bottoms","order":6,"bonuses":[{"type":"naval_attrition","value":"-0.25"}]},{"name":"massed_battery","order":7,"bonuses":[{"type":"artillery_power","value":"0.1"}]}],"important":false},{"isUnique":false,"countryTag":"quantity","type":"quantity_ideas","category":"MIL","ideas":[{"name":"bonus","order":0,"bonuses":[{"type":"land_forcelimit_modifier","value":"0.50"}]},{"name":"mass_army","order":1,"bonuses":[{"type":"global_manpower_modifier","value":"0.50"}]},{"name":"the_young_can_serve","order":2,"bonuses":[{"type":"manpower_recovery_speed","value":"0.20"}]},{"name":"enforced_service","order":3,"bonuses":[{"type":"global_regiment_cost","value":"-0.1"}]},{"name":"the_old_and_infirm","order":4,"bonuses":[{"type":"land_maintenance_modifier","value":"-0.05"}]},{"name":"camp_followers","order":5,"bonuses":[{"type":"global_supply_limit_modifier","value":"0.33"}]},{"name":"garrison_conscription","order":6,"bonuses":[{"type":"free_leader_pool","value":"1"}]},{"name":"expanded_supply_trains","order":7,"bonuses":[{"type":"land_attrition","value":"-0.1"}]}],"important":false},{"isUnique":false,"countryTag":"expansion","type":"expansion_ideas","category":"ADM","ideas":[{"name":"bonus","order":0,"bonuses":[{"type":"governing_capacity","value":"400"},{"type":"governing_capacity_modifier","value":"0.15"}]},{"name":"adaptability","order":1,"bonuses":[{"type":"core_creation","value":"-0.33"}]},{"name":"additional_merchants","order":2,"bonuses":[{"type":"merchants","value":"2"},{"type":"placed_merchant_power","value":"10"}]},{"name":"exp_bill_of_rights","order":3,"bonuses":[{"type":"global_unrest","value":"-2"},{"type":"num_accepted_cultures","value":"3"}]},{"name":"factories","order":4,"bonuses":[{"type":"years_of_nationalism","value":"-10"},{"type":"trade_company_investment_cost","value":"-0.25"}]},{"name":"competetive_merchants","order":5,"bonuses":[{"type":"global_trade_power","value":"0.25"},{"type":"global_trade_goods_size_modifier","value":"0.1"}]},{"name":"exp_free_subjects","order":6,"bonuses":[{"type":"manpower_recovery_speed","value":"0.2"}]},{"name":"additional_diplomats","order":7,"bonuses":[{"type":"land_attrition","value":"-0.2"}]}],"important":true},{"isUnique":false,"countryTag":"administrative","type":"administrative_ideas","category":"ADM","ideas":[{"name":"bonus","order":0,"bonuses":[{"type":"advisor_cost","value":"-0.25"}]},{"name":"adm_adaptability","order":1,"bonuses":[{"type":"reform_progress_growth","value":"0.5"}]},{"name":"organised_mercenary_payment","order":2,"bonuses":[{"type":"state_maintenance_modifier","value":"-0.5"}]},{"name":"civil_servants","order":3,"bonuses":[{"type":"monthly_splendor","value":"3"},{"type":"advisor_pool","value":"2"}]},{"name":"benefits_for_mercenaries","order":4,"bonuses":[{"type":"merc_maintenance_modifier","value":"-0.5"}]},{"name":"bookkeeping","order":5,"bonuses":[{"type":"interest","value":"-0.25"}]},{"name":"organised_mercenary_recruitment","order":6,"bonuses":[{"type":"expand_administration_cost","value":"-0.75"}]},{"name":"administrative_efficiency_idea","order":7,"bonuses":[{"type":"free_policy","value":"1"}]}],"important":false},{"isUnique":false,"countryTag":"humanist","type":"humanist_ideas","category":"ADM","ideas":[{"name":"bonus","order":0,"bonuses":[{"type":"idea_cost","value":"-0.1"},{"type":"yearly_harmony","value":"0.25"},{"type":"brahmins_muslim_loyalty_modifier","value":"0.1"},{"type":"dhimmi_loyalty_modifier","value":"0.1"}]},{"name":"tolerance_idea","order":1,"bonuses":[{"type":"religious_unity","value":"0.25"}]},{"name":"local_traditions","order":2,"bonuses":[{"type":"global_unrest","value":"-2"}]},{"name":"ecumenism","order":3,"bonuses":[{"type":"tolerance_heretic","value":"2"}]},{"name":"indirect_rule","order":4,"bonuses":[{"type":"years_of_nationalism","value":"-10"}]},{"name":"cultural_ties","order":5,"bonuses":[{"type":"num_accepted_cultures","value":"2"}]},{"name":"benevolence","order":6,"bonuses":[{"type":"improve_relation_modifier","value":"0.3"}]},{"name":"humanist_tolerance","order":7,"bonuses":[{"type":"tolerance_heathen","value":"2"}]}],"trigger":{"primatives":true,"tag":[]},"important":false},{"isUnique":false,"countryTag":"influence","type":"influence_ideas","category":"DIP","ideas":[{"name":"bonus","order":0,"bonuses":[{"type":"reduced_stab_impacts","value":"yes"}]},{"name":"tribute_system","order":1,"bonuses":[{"type":"war_exhaustion","value":"-0.05"},{"type":"dip_tech_cost_modifier","value":"-0.1"}]},{"name":"additional_loyalist_recruitment","order":2,"bonuses":[{"type":"reduced_liberty_desire","value":"25"},{"type":"province_warscore_cost","value":"-0.2"}]},{"name":"diplomatic_influence","order":3,"bonuses":[{"type":"diplomatic_reputation","value":"5"},{"type":"accept_vassalization_reasons","value":"10"}]},{"name":"integrated_elites","order":4,"bonuses":[{"type":"diplomatic_annexation_cost","value":"-0.25"}]},{"name":"buffer_states","order":5,"bonuses":[{"type":"global_own_trade_power","value":"0.25"},{"type":"diplomatic_upkeep","value":"2"}]},{"name":"inf_flexible_negotiation","order":6,"bonuses":[{"type":"center_of_trade_upgrade_cost","value":"-0.25"},{"type":"mercantilism_cost","value":"-0.25"}]},{"name":"marcher_lords","order":7,"bonuses":[{"type":"vassal_forcelimit_bonus","value":"1"},{"type":"can_fabricate_for_vassals","value":"yes"}]}],"important":false},{"isUnique":false,"countryTag":"naval","type":"naval_ideas","category":"MIL","ideas":[{"name":"bonus","order":0,"bonuses":[{"type":"ship_durability","value":"0.1"},{"type":"allowed_marine_fraction","value":"0.05"}]},{"name":"boarding_parties","order":1,"bonuses":[{"type":"leader_naval_shock","value":"1"}]},{"name":"improved_rams","order":2,"bonuses":[{"type":"galley_power","value":"0.25"}]},{"name":"naval_cadets","order":3,"bonuses":[{"type":"leader_naval_fire","value":"1"},{"type":"sunk_ship_morale_hit_recieved","value":"-0.33"}]},{"name":"naval_glory","order":4,"bonuses":[{"type":"navy_tradition","value":"1"}]},{"name":"press_gangs","order":5,"bonuses":[{"type":"sailors_recovery_speed","value":"0.25"}]},{"name":"oak_forests_for_ships","order":6,"bonuses":[{"type":"heavy_ship_power","value":"0.20"}]},{"name":"superior_seamanship","order":7,"bonuses":[{"type":"naval_morale","value":"0.1"},{"type":"global_naval_engagement_modifier","value":"0.1"}]}],"trigger":{"primatives":true,"tag":[]},"important":false}]}